centerofgravity
