Metadata-Version: 1.1
Name: centerofgravity
Version: 1.0.1
Summary: Automated Center of Gravity Mapping
Home-page: https://github.com/abrammoats/centerofgravity
Author: Scott Mutchler, Abram Moats
Author-email: smutchler@trilabyte.com, abramdanielmoats@gmail.com
License: GPLv3
Download-URL: https://github.com/abrammoats/centerofgravity/archive/refs/tags/1.0.1.tar.gz
Keywords: CENTROID,MAPPING,VISUALIZATION,CLUSTERING
Platform: UNKNOWN
Classifier: Development Status :: 3 - Alpha
Classifier: Intended Audience :: Developers
Classifier: Topic :: Software Development :: Build Tools
